KingDataGenerators
