Metadata-Version: 2.1
Name: KingDataGenerators
Version: 1.2
Summary: This packet generates fictitious human data, uniquely (names,emails,password,personal-documents), for the use of the develpoer
Author: Black King
Author-email: docomeco2k20@gmail.com
Keywords: data human,fordev,4dev,generator,dados pessoais,gerador
License-File: license.txt
